fixtures_mongoengine
