Metadata-Version: 1.1
Name: fixtures-mongoengine
Version: 1.3.0
Summary: MongoEngine Fixtures.
Home-page: https://github.com/coderfly/fixtures-mongoengine/
Author: Vitaly Nikitin
Author-email: alaris.nik@gmail.com
License: UNKNOWN
Download-URL: https://github.com/coderfly/fixtures-mongoengine/tarball/1.3.0
Keywords: testing,fixtures,mongoengine
Platform: UNKNOWN
